setup.py
src/__init__.py
src/logic.py
src/main.py
testprojsachin.egg-info/PKG-INFO
testprojsachin.egg-info/SOURCES.txt
testprojsachin.egg-info/dependency_links.txt
testprojsachin.egg-info/entry_points.txt
testprojsachin.egg-info/requires.txt
testprojsachin.egg-info/top_level.txt