Metadata-Version: 2.1
Name: testprojsachin
Version: 0.0.4
Summary: An application that informs you of the time in different locations and timezones
Home-page: https://github.com/sac1103/pythonpacks.git
Author: sachin
Author-email: reachsachinquick@gmail.com
Classifier: Programming Language :: Python :: 3
Classifier: License :: OSI Approved :: MIT License
Classifier: Operating System :: OS Independent
